Metadata-Version: 1.0
Name: legitfs
Version: 0.4.0
Summary: A read-only FUSE-based filesystem allowing you to browse git repositories
Home-page: http://github.com/mbr/legitfs
Author: Marc Brinkmann
Author-email: git@marcbrinkmann.de
License: MIT
Keywords: git,fuse,filesystem,fs,read-only,readonly,legit,legitfs
Platform: UNKNOWN
